README.md
setup.py
elasticsearch_loader/__init__.py
elasticsearch_loader/__main__.py
elasticsearch_loader/iter.py
elasticsearch_loader/parsers.py
elasticsearch_loader.egg-info/PKG-INFO
elasticsearch_loader.egg-info/SOURCES.txt
elasticsearch_loader.egg-info/dependency_links.txt
elasticsearch_loader.egg-info/entry_points.txt
elasticsearch_loader.egg-info/requires.txt
elasticsearch_loader.egg-info/top_level.txt
test/test_csv.py
test/test_end_to_end.py
test/test_json.py
test/test_jsonlines.py