Metadata-Version: 2.1
Name: elasticsearch-loader
Version: 0.5.1
Summary: A pythonic tool for batch loading data files (json, parquet, csv, tsv) into ElasticSearch
Home-page: https://github.com/Moshe/elasticsearch_loader
Author: Moshe Zada
License: UNKNOWN
Keywords: elastic,elasticsearch,csv,json,parquet,bulk,loader,redis
Platform: UNKNOWN
Provides-Extra: s3
Provides-Extra: parquet
Provides-Extra: redis
Provides-Extra: tests
